gut/__init__.py
gut/_banner.py
gut/main.py
gut/models.py
gut/shell.py
gut/utils.py
gut/workflow/__init__.py
gut/workflow/commands.py
gut/workflow/events.py
gut/workflow/flow.py
gut/workflow/resources.py
gut_ai-0.3.1.dist-info/METADATA
gut_ai-0.3.1.dist-info/WHEEL
gut_ai-0.3.1.dist-info/entry_points.txt
gut_ai-0.3.1.dist-info/licenses/LICENSE
gut_ai-0.3.1.dist-info/RECORD
