Metadata-Version: 2.4
Name: gut-ai
Version: 0.3.1
Summary: Add your description here
License-File: LICENSE
Requires-Python: >=3.13
Requires-Dist: click>=8.2.1
Requires-Dist: llama-index-llms-groq>=0.3.2
Requires-Dist: llama-index-workflows>=1.1.0
Requires-Dist: mypy>=1.17.0
Requires-Dist: pre-commit>=4.2.0
Requires-Dist: pydantic>=2.11.7
Requires-Dist: pytest-asyncio>=1.1.0
Requires-Dist: pytest>=8.4.1
Requires-Dist: python-dotenv>=1.1.1
Requires-Dist: rich>=14.0.0
